{"_ts":[1488327370],"_r":{"breakdown":{"html":{"bytes":[18313],"requests":[1]},"js":{"bytes":[88593],"requests":[6]},"css":{"bytes":[34269],"requests":[9]},"image":{"bytes":[82191],"requests":[9]},"flash":{"bytes":[0],"requests":[0]},"font":{"bytes":[0],"requests":[0]},"other":{"bytes":[23201],"requests":[1]}},"date":[1488327370],"domElements":[1244],"domInteractive":[750],"firstPaint":[1295],"fullyLoaded":[2266],"id":["170301_5B_SG"],"loadTime":[1605],"render":[1713],"SpeedIndex":[1723],"TTFB":[320],"videoFrames":[[{"_t":0,"_vc":0},{"_t":1700,"_vc":87},{"_t":1800,"_vc":100},{"_t":2200,"_vc":100},{"_t":2400,"_vc":100}]],"visualComplete":[1803]}}